LICENSE.txt
MANIFEST.in
README.md
setup.cfg
setup.py
flaskfilemanager/__init__.py
flaskfilemanager/filemanager.py
flaskfilemanager.egg-info/PKG-INFO
flaskfilemanager.egg-info/SOURCES.txt
flaskfilemanager.egg-info/dependency_links.txt
flaskfilemanager.egg-info/requires.txt
flaskfilemanager.egg-info/top_level.txt
flaskfilemanager/RichFilemanager/ReadMe.md
flaskfilemanager/RichFilemanager/bower.json
flaskfilemanager/RichFilemanager/changelog
flaskfilemanager/RichFilemanager/composer.json
flaskfilemanager/RichFilemanager/index.html
flaskfilemanager/RichFilemanager/package.json
flaskfilemanager/RichFilemanager/config/filemanager.config.default.json
flaskfilemanager/RichFilemanager/config/filemanager.config.json
flaskfilemanager/RichFilemanager/config/filemanager.init.js
flaskfilemanager/RichFilemanager/config/filemanager.init.js.example
flaskfilemanager/RichFilemanager/images/accept.png
flaskfilemanager/RichFilemanager/images/ajax-loader.gif
flaskfilemanager/RichFilemanager/images/application_view_icons.png
flaskfilemanager/RichFilemanager/images/application_view_list.png
flaskfilemanager/RichFilemanager/images/bin_closed.png
flaskfilemanager/RichFilemanager/images/bullet_arrow_down.png
flaskfilemanager/RichFilemanager/images/bullet_arrow_up.png
flaskfilemanager/RichFilemanager/images/copy.png
flaskfilemanager/RichFilemanager/images/copy_url.png
flaskfilemanager/RichFilemanager/images/download.png
flaskfilemanager/RichFilemanager/images/edit.png
flaskfilemanager/RichFilemanager/images/edit_dark.png
flaskfilemanager/RichFilemanager/images/extract.png
flaskfilemanager/RichFilemanager/images/fmlogo.png
flaskfilemanager/RichFilemanager/images/folder_add.png
flaskfilemanager/RichFilemanager/images/house.png
flaskfilemanager/RichFilemanager/images/info.png
flaskfilemanager/RichFilemanager/images/move.png
flaskfilemanager/RichFilemanager/images/parentfolder.png
flaskfilemanager/RichFilemanager/images/plus.png
flaskfilemanager/RichFilemanager/images/replace.png
flaskfilemanager/RichFilemanager/images/reset.png
flaskfilemanager/RichFilemanager/images/reset_dark.png
flaskfilemanager/RichFilemanager/images/save.png
flaskfilemanager/RichFilemanager/images/save_dark.png
