Metadata-Version: 1.1
Name: flaskfilemanager
Version: 0.0.6
Summary: RichFilemanager blueprint for Flask web applications - adds a ckeditor compatible file manager / browser
Home-page: https://github.com/stevelittlefish/flaskfilemanager
Author: Stephen Brown (Little Fish Solutions LTD)
Author-email: opensource@littlefish.solutions
License: Apache
Download-URL: https://github.com/stevelittlefish/flaskfilemanager/archive/v0.0.6.tar.gz
Keywords: flask,jinja2,filemanager,file,manager,browser,ckeditor
Platform: UNKNOWN
Classifier: License :: OSI Approved :: Apache Software License
Classifier: Framework :: Flask
Classifier: Development Status :: 5 - Production/Stable
Classifier: Intended Audience :: Developers
Classifier: Programming Language :: Python :: 3
Classifier: Topic :: Software Development :: Libraries
